Workbook

Sheet Registro de Gastos
A1: CONTROL DE GASTOS — SOCIEDAD VARGAS MESA
A2: Fincas: Palosolo, El Japón y San José | Solo Sofía Vargas y Eufracio Vargas
A3: Fecha | B3: Descripción del Gasto | C3: Categoría | D3: Subcategoría | E3: Finca | F3: Proveedor | G3: Total ($COP) | H3: Registrado por | I3: Notas
A104: TOTAL GENERAL | G104: =SUM(G4:G103)

Sheet Resumen por Categoría
A1: RESUMEN DE GASTOS POR CATEGORÍA
A2: Filtrar por Finca: | B2: Todas | C2: ← Seleccionar finca o 'Todas'
A3: Fecha Inicio (rango): | C3: ← Clic en la celda y usa el selector de fecha
A4: Fecha Fin (rango): | C4: ← Clic en la celda y usa el selector de fecha
A6: 📅 MES ACTUAL
A7: Categoría | B7: Total ($COP) | C7: % del Total | D7: vs Presupuesto ($) | E7: Desv. % | F7: Nivel | G7: Finca
A8: Droga veterinaria | B8: =SUMPRODUCT(('Registro de Gastos'!C4:C103=A8)*(IFERROR(MONTH('Registro de Gastos'!A4:A103),0)=MONTH(TODAY()))*(IFERROR(YEAR('Registro de Gastos'!A4:A103),0)=YEAR(TODAY()))*((B$2="Todas")+('Registro de Gastos'!E4:E103=B$2)>0)*'Registro de Gastos'!G4:G103) | C8: =IF(B17=0,"-",B8/B17) | D8: =B8-Presupuesto!B4 | E8: =IF(Presupuesto!B4=0,"-",B8/Presupuesto!B4-1) | F8: =IF(C8="-","-",IF(C8>0.35,"🔴 Alto",IF(C8>0.15,"🟡 Medio","🟢 Bajo"))) | G8: =B$2
A9: Insumos | B9: =SUMPRODUCT(('Registro de Gastos'!C4:C103=A9)*(IFERROR(MONTH('Registro de Gastos'!A4:A103),0)=MONTH(TODAY()))*(IFERROR(YEAR('Registro de Gastos'!A4:A103),0)=YEAR(TODAY()))*((B$2="Todas")+('Registro de Gastos'!E4:E103=B$2)>0)*'Registro de Gastos'!G4:G103) | C9: =IF(B17=0,"-",B9/B17) | D9: =B9-Presupuesto!B5 | E9: =IF(Presupuesto!B5=0,"-",B9/Presupuesto!B5-1) | F9: =IF(C9="-","-",IF(C9>0.35,"🔴 Alto",IF(C9>0.15,"🟡 Medio","🟢 Bajo"))) | G9: =B$2
A10: Mano de obra | B10: =SUMPRODUCT(('Registro de Gastos'!C4:C103=A10)*(IFERROR(MONTH('Registro de Gastos'!A4:A103),0)=MONTH(TODAY()))*(IFERROR(YEAR('Registro de Gastos'!A4:A103),0)=YEAR(TODAY()))*((B$2="Todas")+('Registro de Gastos'!E4:E103=B$2)>0)*'Registro de Gastos'!G4:G103) | C10: =IF(B17=0,"-",B10/B17) | D10: =B10-Presupuesto!B6 | E10: =IF(Presupuesto!B6=0,"-",B10/Presupuesto!B6-1) | F10: =IF(C10="-","-",IF(C10>0.35,"🔴 Alto",IF(C10>0.15,"🟡 Medio","🟢 Bajo"))) | G10: =B$2
A11: Equipos y mantenimiento | B11: =SUMPRODUCT(('Registro de Gastos'!C4:C103=A11)*(IFERROR(MONTH('Registro de Gastos'!A4:A103),0)=MONTH(TODAY()))*(IFERROR(YEAR('Registro de Gastos'!A4:A103),0)=YEAR(TODAY()))*((B$2="Todas")+('Registro de Gastos'!E4:E103=B$2)>0)*'Registro de Gastos'!G4:G103) | C11: =IF(B17=0,"-",B11/B17) | D11: =B11-Presupuesto!B7 | E11: =IF(Presupuesto!B7=0,"-",B11/Presupuesto!B7-1) | F11: =IF(C11="-","-",IF(C11>0.35,"🔴 Alto",IF(C11>0.15,"🟡 Medio","🟢 Bajo"))) | G11: =B$2
A12: Transporte | B12: =SUMPRODUCT(('Registro de Gastos'!C4:C103=A12)*(IFERROR(MONTH('Registro de Gastos'!A4:A103),0)=MONTH(TODAY()))*(IFERROR(YEAR('Registro de Gastos'!A4:A103),0)=YEAR(TODAY()))*((B$2="Todas")+('Registro de Gastos'!E4:E103=B$2)>0)*'Registro de Gastos'!G4:G103) | C12: =IF(B17=0,"-",B12/B17) | D12: =B12-Presupuesto!B8 | E12: =IF(Presupuesto!B8=0,"-",B12/Presupuesto!B8-1) | F12: =IF(C12="-","-",IF(C12>0.35,"🔴 Alto",IF(C12>0.15,"🟡 Medio","🟢 Bajo"))) | G12: =B$2
A13: Víveres y mercado | B13: =SUMPRODUCT(('Registro de Gastos'!C4:C103=A13)*(IFERROR(MONTH('Registro de Gastos'!A4:A103),0)=MONTH(TODAY()))*(IFERROR(YEAR('Registro de Gastos'!A4:A103),0)=YEAR(TODAY()))*((B$2="Todas")+('Registro de Gastos'!E4:E103=B$2)>0)*'Registro de Gastos'!G4:G103) | C13: =IF(B17=0,"-",B13/B17) | D13: =B13-Presupuesto!B9 | E13: =IF(Presupuesto!B9=0,"-",B13/Presupuesto!B9-1) | F13: =IF(C13="-","-",IF(C13>0.35,"🔴 Alto",IF(C13>0.15,"🟡 Medio","🟢 Bajo"))) | G13: =B$2
A14: Locativos | B14: =SUMPRODUCT(('Registro de Gastos'!C4:C103=A14)*(IFERROR(MONTH('Registro de Gastos'!A4:A103),0)=MONTH(TODAY()))*(IFERROR(YEAR('Registro de Gastos'!A4:A103),0)=YEAR(TODAY()))*((B$2="Todas")+('Registro de Gastos'!E4:E103=B$2)>0)*'Registro de Gastos'!G4:G103) | C14: =IF(B17=0,"-",B14/B17) | D14: =B14-Presupuesto!B10 | E14: =IF(Presupuesto!B10=0,"-",B14/Presupuesto!B10-1) | F14: =IF(C14="-","-",IF(C14>0.35,"🔴 Alto",IF(C14>0.15,"🟡 Medio","🟢 Bajo"))) | G14: =B$2
A15: Servicios públicos | B15: =SUMPRODUCT(('Registro de Gastos'!C4:C103=A15)*(IFERROR(MONTH('Registro de Gastos'!A4:A103),0)=MONTH(TODAY()))*(IFERROR(YEAR('Registro de Gastos'!A4:A103),0)=YEAR(TODAY()))*((B$2="Todas")+('Registro de Gastos'!E4:E103=B$2)>0)*'Registro de Gastos'!G4:G103) | C15: =IF(B17=0,"-",B15/B17) | D15: =B15-Presupuesto!B11 | E15: =IF(Presupuesto!B11=0,"-",B15/Presupuesto!B11-1) | F15: =IF(C15="-","-",IF(C15>0.35,"🔴 Alto",IF(C15>0.15,"🟡 Medio","🟢 Bajo"))) | G15: =B$2
A16: Otros | B16: =SUMPRODUCT(('Registro de Gastos'!C4:C103=A16)*(IFERROR(MONTH('Registro de Gastos'!A4:A103),0)=MONTH(TODAY()))*(IFERROR(YEAR('Registro de Gastos'!A4:A103),0)=YEAR(TODAY()))*((B$2="Todas")+('Registro de Gastos'!E4:E103=B$2)>0)*'Registro de Gastos'!G4:G103) | C16: =IF(B17=0,"-",B16/B17) | D16: =B16-Presupuesto!B12 | E16: =IF(Presupuesto!B12=0,"-",B16/Presupuesto!B12-1) | F16: =IF(C16="-","-",IF(C16>0.35,"🔴 Alto",IF(C16>0.15,"🟡 Medio","🟢 Bajo"))) | G16: =B$2
A17: TOTAL | B17: =SUM(B8:B16)
A19: 📆 ACUMULADO AÑO
A20: Categoría | B20: Total ($COP) | C20: % del Total | D20: vs Presupuesto ($) | E20: Desv. % | F20: Nivel | G20: Finca
A21: Droga veterinaria | B21: =SUMPRODUCT(('Registro de Gastos'!C4:C103=A21)*(IFERROR(YEAR('Registro de Gastos'!A4:A103),0)=YEAR(TODAY()))*((B$2="Todas")+('Registro de Gastos'!E4:E103=B$2)>0)*'Registro de Gastos'!G4:G103) | C21: =IF(B30=0,"-",B21/B30) | D21: — | E21: — | F21: =IF(C21="-","-",IF(C21>0.35,"🔴 Alto",IF(C21>0.15,"🟡 Medio","🟢 Bajo"))) | G21: =B$2
A22: Insumos | B22: =SUMPRODUCT(('Registro de Gastos'!C4:C103=A22)*(IFERROR(YEAR('Registro de Gastos'!A4:A103),0)=YEAR(TODAY()))*((B$2="Todas")+('Registro de Gastos'!E4:E103=B$2)>0)*'Registro de Gastos'!G4:G103) | C22: =IF(B30=0,"-",B22/B30) | D22: — | E22: — | F22: =IF(C22="-","-",IF(C22>0.35,"🔴 Alto",IF(C22>0.15,"🟡 Medio","🟢 Bajo"))) | G22: =B$2
A23: Mano de obra | B23: =SUMPRODUCT(('Registro de Gastos'!C4:C103=A23)*(IFERROR(YEAR('Registro de Gastos'!A4:A103),0)=YEAR(TODAY()))*((B$2="Todas")+('Registro de Gastos'!E4:E103=B$2)>0)*'Registro de Gastos'!G4:G103) | C23: =IF(B30=0,"-",B23/B30) | D23: — | E23: — | F23: =IF(C23="-","-",IF(C23>0.35,"🔴 Alto",IF(C23>0.15,"🟡 Medio","🟢 Bajo"))) | G23: =B$2
A24: Equipos y mantenimiento | B24: =SUMPRODUCT(('Registro de Gastos'!C4:C103=A24)*(IFERROR(YEAR('Registro de Gastos'!A4:A103),0)=YEAR(TODAY()))*((B$2="Todas")+('Registro de Gastos'!E4:E103=B$2)>0)*'Registro de Gastos'!G4:G103) | C24: =IF(B30=0,"-",B24/B30) | D24: — | E24: — | F24: =IF(C24="-","-",IF(C24>0.35,"🔴 Alto",IF(C24>0.15,"🟡 Medio","🟢 Bajo"))) | G24: =B$2
A25: Transporte | B25: =SUMPRODUCT(('Registro de Gastos'!C4:C103=A25)*(IFERROR(YEAR('Registro de Gastos'!A4:A103),0)=YEAR(TODAY()))*((B$2="Todas")+('Registro de Gastos'!E4:E103=B$2)>0)*'Registro de Gastos'!G4:G103) | C25: =IF(B30=0,"-",B25/B30) | D25: — | E25: — | F25: =IF(C25="-","-",IF(C25>0.35,"🔴 Alto",IF(C25>0.15,"🟡 Medio","🟢 Bajo"))) | G25: =B$2
A26: Víveres y mercado | B26: =SUMPRODUCT(('Registro de Gastos'!C4:C103=A26)*(IFERROR(YEAR('Registro de Gastos'!A4:A103),0)=YEAR(TODAY()))*((B$2="Todas")+('Registro de Gastos'!E4:E103=B$2)>0)*'Registro de Gastos'!G4:G103) | C26: =IF(B30=0,"-",B26/B30) | D26: — | E26: — | F26: =IF(C26="-","-",IF(C26>0.35,"🔴 Alto",IF(C26>0.15,"🟡 Medio","🟢 Bajo"))) | G26: =B$2
A27: Locativos | B27: =SUMPRODUCT(('Registro de Gastos'!C4:C103=A27)*(IFERROR(YEAR('Registro de Gastos'!A4:A103),0)=YEAR(TODAY()))*((B$2="Todas")+('Registro de Gastos'!E4:E103=B$2)>0)*'Registro de Gastos'!G4:G103) | C27: =IF(B30=0,"-",B27/B30) | D27: — | E27: — | F27: =IF(C27="-","-",IF(C27>0.35,"🔴 Alto",IF(C27>0.15,"🟡 Medio","🟢 Bajo"))) | G27: =B$2
A28: Servicios públicos | B28: =SUMPRODUCT(('Registro de Gastos'!C4:C103=A28)*(IFERROR(YEAR('Registro de Gastos'!A4:A103),0)=YEAR(TODAY()))*((B$2="Todas")+('Registro de Gastos'!E4:E103=B$2)>0)*'Registro de Gastos'!G4:G103) | C28: =IF(B30=0,"-",B28/B30) | D28: — | E28: — | F28: =IF(C28="-","-",IF(C28>0.35,"🔴 Alto",IF(C28>0.15,"🟡 Medio","🟢 Bajo"))) | G28: =B$2
A29: Otros | B29: =SUMPRODUCT(('Registro de Gastos'!C4:C103=A29)*(IFERROR(YEAR('Registro de Gastos'!A4:A103),0)=YEAR(TODAY()))*((B$2="Todas")+('Registro de Gastos'!E4:E103=B$2)>0)*'Registro de Gastos'!G4:G103) | C29: =IF(B30=0,"-",B29/B30) | D29: — | E29: — | F29: =IF(C29="-","-",IF(C29>0.35,"🔴 Alto",IF(C29>0.15,"🟡 Medio","🟢 Bajo"))) | G29: =B$2
A30: TOTAL | B30: =SUM(B21:B29)
A32: 🗓 RANGO PERSONALIZADO (fechas en B3:B4)
A33: Categoría | B33: Total ($COP) | C33: % del Total | D33: vs Presupuesto ($) | E33: Desv. % | F33: Nivel | G33: Finca
A34: Droga veterinaria | B34: =SUMPRODUCT(('Registro de Gastos'!C4:C103=A34)*('Registro de Gastos'!A4:A103>=(IF(B$3="",DATE(1900,1,1),B$3)))*ISNUMBER('Registro de Gastos'!A4:A103)*('Registro de Gastos'!A4:A103<=(IF(B$4="",TODAY(),B$4)))*((B$2="Todas")+('Registro de Gastos'!E4:E103=B$2)>0)*'Registro de Gastos'!G4:G103) | C34: =IF(B43=0,"-",B34/B43) | D34: — | E34: — | F34: =IF(C34="-","-",IF(C34>0.35,"🔴 Alto",IF(C34>0.15,"🟡 Medio","🟢 Bajo"))) | G34: =B$2
A35: Insumos | B35: =SUMPRODUCT(('Registro de Gastos'!C4:C103=A35)*('Registro de Gastos'!A4:A103>=(IF(B$3="",DATE(1900,1,1),B$3)))*ISNUMBER('Registro de Gastos'!A4:A103)*('Registro de Gastos'!A4:A103<=(IF(B$4="",TODAY(),B$4)))*((B$2="Todas")+('Registro de Gastos'!E4:E103=B$2)>0)*'Registro de Gastos'!G4:G103) | C35: =IF(B43=0,"-",B35/B43) | D35: — | E35: — | F35: =IF(C35="-","-",IF(C35>0.35,"🔴 Alto",IF(C35>0.15,"🟡 Medio","🟢 Bajo"))) | G35: =B$2
A36: Mano de obra | B36: =SUMPRODUCT(('Registro de Gastos'!C4:C103=A36)*('Registro de Gastos'!A4:A103>=(IF(B$3="",DATE(1900,1,1),B$3)))*ISNUMBER('Registro de Gastos'!A4:A103)*('Registro de Gastos'!A4:A103<=(IF(B$4="",TODAY(),B$4)))*((B$2="Todas")+('Registro de Gastos'!E4:E103=B$2)>0)*'Registro de Gastos'!G4:G103) | C36: =IF(B43=0,"-",B36/B43) | D36: — | E36: — | F36: =IF(C36="-","-",IF(C36>0.35,"🔴 Alto",IF(C36>0.15,"🟡 Medio","🟢 Bajo"))) | G36: =B$2
A37: Equipos y mantenimiento | B37: =SUMPRODUCT(('Registro de Gastos'!C4:C103=A37)*('Registro de Gastos'!A4:A103>=(IF(B$3="",DATE(1900,1,1),B$3)))*ISNUMBER('Registro de Gastos'!A4:A103)*('Registro de Gastos'!A4:A103<=(IF(B$4="",TODAY(),B$4)))*((B$2="Todas")+('Registro de Gastos'!E4:E103=B$2)>0)*'Registro de Gastos'!G4:G103) | C37: =IF(B43=0,"-",B37/B43) | D37: — | E37: — | F37: =IF(C37="-","-",IF(C37>0.35,"🔴 Alto",IF(C37>0.15,"🟡 Medio","🟢 Bajo"))) | G37: =B$2
A38: Transporte | B38: =SUMPRODUCT(('Registro de Gastos'!C4:C103=A38)*('Registro de Gastos'!A4:A103>=(IF(B$3="",DATE(1900,1,1),B$3)))*ISNUMBER('Registro de Gastos'!A4:A103)*('Registro de Gastos'!A4:A103<=(IF(B$4="",TODAY(),B$4)))*((B$2="Todas")+('Registro de Gastos'!E4:E103=B$2)>0)*'Registro de Gastos'!G4:G103) | C38: =IF(B43=0,"-",B38/B43) | D38: — | E38: — | F38: =IF(C38="-","-",IF(C38>0.35,"🔴 Alto",IF(C38>0.15,"🟡 Medio","🟢 Bajo"))) | G38: =B$2
A39: Víveres y mercado | B39: =SUMPRODUCT(('Registro de Gastos'!C4:C103=A39)*('Registro de Gastos'!A4:A103>=(IF(B$3="",DATE(1900,1,1),B$3)))*ISNUMBER('Registro de Gastos'!A4:A103)*('Registro de Gastos'!A4:A103<=(IF(B$4="",TODAY(),B$4)))*((B$2="Todas")+('Registro de Gastos'!E4:E103=B$2)>0)*'Registro de Gastos'!G4:G103) | C39: =IF(B43=0,"-",B39/B43) | D39: — | E39: — | F39: =IF(C39="-","-",IF(C39>0.35,"🔴 Alto",IF(C39>0.15,"🟡 Medio","🟢 Bajo"))) | G39: =B$2
A40: Locativos | B40: =SUMPRODUCT(('Registro de Gastos'!C4:C103=A40)*('Registro de Gastos'!A4:A103>=(IF(B$3="",DATE(1900,1,1),B$3)))*ISNUMBER('Registro de Gastos'!A4:A103)*('Registro de Gastos'!A4:A103<=(IF(B$4="",TODAY(),B$4)))*((B$2="Todas")+('Registro de Gastos'!E4:E103=B$2)>0)*'Registro de Gastos'!G4:G103) | C40: =IF(B43=0,"-",B40/B43) | D40: — | E40: — | F40: =IF(C40="-","-",IF(C40>0.35,"🔴 Alto",IF(C40>0.15,"🟡 Medio","🟢 Bajo"))) | G40: =B$2
A41: Servicios públicos | B41: =SUMPRODUCT(('Registro de Gastos'!C4:C103=A41)*('Registro de Gastos'!A4:A103>=(IF(B$3="",DATE(1900,1,1),B$3)))*ISNUMBER('Registro de Gastos'!A4:A103)*('Registro de Gastos'!A4:A103<=(IF(B$4="",TODAY(),B$4)))*((B$2="Todas")+('Registro de Gastos'!E4:E103=B$2)>0)*'Registro de Gastos'!G4:G103) | C41: =IF(B43=0,"-",B41/B43) | D41: — | E41: — | F41: =IF(C41="-","-",IF(C41>0.35,"🔴 Alto",IF(C41>0.15,"🟡 Medio","🟢 Bajo"))) | G41: =B$2
A42: Otros | B42: =SUMPRODUCT(('Registro de Gastos'!C4:C103=A42)*('Registro de Gastos'!A4:A103>=(IF(B$3="",DATE(1900,1,1),B$3)))*ISNUMBER('Registro de Gastos'!A4:A103)*('Registro de Gastos'!A4:A103<=(IF(B$4="",TODAY(),B$4)))*((B$2="Todas")+('Registro de Gastos'!E4:E103=B$2)>0)*'Registro de Gastos'!G4:G103) | C42: =IF(B43=0,"-",B42/B43) | D42: — | E42: — | F42: =IF(C42="-","-",IF(C42>0.35,"🔴 Alto",IF(C42>0.15,"🟡 Medio","🟢 Bajo"))) | G42: =B$2
A43: TOTAL | B43: =SUM(B34:B42)

Sheet Dashboard
A1: 📊 DASHBOARD — CONTROL DE GASTOS SOCIEDAD VARGAS MESA
A2: INDICADORES CLAVE — MES ACTUAL
A3: PRESUPUESTO MENSUAL | C3: GASTO MES ACTUAL | E3: % EJECUCIÓN | G3: GASTO ANUAL | I3: TRANSACCIONES MES | K3: SEMÁFORO PRESUPUESTAL
A4: =Presupuesto!C2 | C4: =SUMPRODUCT((MONTH('Registro de Gastos'!A4:A103)=MONTH(TODAY()))*(YEAR('Registro de Gastos'!A4:A103)=YEAR(TODAY()))*'Registro de Gastos'!G4:G103) | E4: =IF(Presupuesto!C2=0,"-",C4/Presupuesto!C2) | G4: =SUMPRODUCT((YEAR('Registro de Gastos'!A4:A103)=YEAR(TODAY()))*'Registro de Gastos'!G4:G103) | I4: =COUNTIFS('Registro de Gastos'!A4:A103,">="&DATE(YEAR(TODAY()),MONTH(TODAY()),1),'Registro de Gastos'!A4:A103,"<="&EOMONTH(TODAY(),0)) | K4: =IF(Presupuesto!C2=0,"N/D",IF(C4/Presupuesto!C2<=0.8,"🟢 NORMAL",IF(C4/Presupuesto!C2<=1,"🟡 ELEVADO","🔴 CRÍTICO")))
A6: MES | B6: GASTOS ($COP) | C6: PRESUPUESTO | E6: CATEGORÍA | F6: GASTO MES ($)
A7: Ene | B7: =SUMPRODUCT((MONTH('Registro de Gastos'!A4:A103)=1)*(YEAR('Registro de Gastos'!A4:A103)=YEAR(TODAY()))*'Registro de Gastos'!G4:G103) | C7: =Presupuesto!$C$2 | E7: Droga veterinaria | F7: =SUMPRODUCT(('Registro de Gastos'!C4:C103=E7)*(MONTH('Registro de Gastos'!A4:A103)=MONTH(TODAY()))*(YEAR('Registro de Gastos'!A4:A103)=YEAR(TODAY()))*'Registro de Gastos'!G4:G103)
A8: Feb | B8: =SUMPRODUCT((MONTH('Registro de Gastos'!A4:A103)=2)*(YEAR('Registro de Gastos'!A4:A103)=YEAR(TODAY()))*'Registro de Gastos'!G4:G103) | C8: =Presupuesto!$C$2 | E8: Insumos | F8: =SUMPRODUCT(('Registro de Gastos'!C4:C103=E8)*(MONTH('Registro de Gastos'!A4:A103)=MONTH(TODAY()))*(YEAR('Registro de Gastos'!A4:A103)=YEAR(TODAY()))*'Registro de Gastos'!G4:G103)
A9: Mar | B9: =SUMPRODUCT((MONTH('Registro de Gastos'!A4:A103)=3)*(YEAR('Registro de Gastos'!A4:A103)=YEAR(TODAY()))*'Registro de Gastos'!G4:G103) | C9: =Presupuesto!$C$2 | E9: Mano de obra | F9: =SUMPRODUCT(('Registro de Gastos'!C4:C103=E9)*(MONTH('Registro de Gastos'!A4:A103)=MONTH(TODAY()))*(YEAR('Registro de Gastos'!A4:A103)=YEAR(TODAY()))*'Registro de Gastos'!G4:G103)
A10: Abr | B10: =SUMPRODUCT((MONTH('Registro de Gastos'!A4:A103)=4)*(YEAR('Registro de Gastos'!A4:A103)=YEAR(TODAY()))*'Registro de Gastos'!G4:G103) | C10: =Presupuesto!$C$2 | E10: Equipos y mantenimiento | F10: =SUMPRODUCT(('Registro de Gastos'!C4:C103=E10)*(MONTH('Registro de Gastos'!A4:A103)=MONTH(TODAY()))*(YEAR('Registro de Gastos'!A4:A103)=YEAR(TODAY()))*'Registro de Gastos'!G4:G103)
A11: May | B11: =SUMPRODUCT((MONTH('Registro de Gastos'!A4:A103)=5)*(YEAR('Registro de Gastos'!A4:A103)=YEAR(TODAY()))*'Registro de Gastos'!G4:G103) | C11: =Presupuesto!$C$2 | E11: Transporte | F11: =SUMPRODUCT(('Registro de Gastos'!C4:C103=E11)*(MONTH('Registro de Gastos'!A4:A103)=MONTH(TODAY()))*(YEAR('Registro de Gastos'!A4:A103)=YEAR(TODAY()))*'Registro de Gastos'!G4:G103)
A12: Jun | B12: =SUMPRODUCT((MONTH('Registro de Gastos'!A4:A103)=6)*(YEAR('Registro de Gastos'!A4:A103)=YEAR(TODAY()))*'Registro de Gastos'!G4:G103) | C12: =Presupuesto!$C$2 | E12: Víveres y mercado | F12: =SUMPRODUCT(('Registro de Gastos'!C4:C103=E12)*(MONTH('Registro de Gastos'!A4:A103)=MONTH(TODAY()))*(YEAR('Registro de Gastos'!A4:A103)=YEAR(TODAY()))*'Registro de Gastos'!G4:G103)
A13: Jul | B13: =SUMPRODUCT((MONTH('Registro de Gastos'!A4:A103)=7)*(YEAR('Registro de Gastos'!A4:A103)=YEAR(TODAY()))*'Registro de Gastos'!G4:G103) | C13: =Presupuesto!$C$2 | E13: Locativos | F13: =SUMPRODUCT(('Registro de Gastos'!C4:C103=E13)*(MONTH('Registro de Gastos'!A4:A103)=MONTH(TODAY()))*(YEAR('Registro de Gastos'!A4:A103)=YEAR(TODAY()))*'Registro de Gastos'!G4:G103)
A14: Ago | B14: =SUMPRODUCT((MONTH('Registro de Gastos'!A4:A103)=8)*(YEAR('Registro de Gastos'!A4:A103)=YEAR(TODAY()))*'Registro de Gastos'!G4:G103) | C14: =Presupuesto!$C$2 | E14: Servicios públicos | F14: =SUMPRODUCT(('Registro de Gastos'!C4:C103=E14)*(MONTH('Registro de Gastos'!A4:A103)=MONTH(TODAY()))*(YEAR('Registro de Gastos'!A4:A103)=YEAR(TODAY()))*'Registro de Gastos'!G4:G103)
A15: Sep | B15: =SUMPRODUCT((MONTH('Registro de Gastos'!A4:A103)=9)*(YEAR('Registro de Gastos'!A4:A103)=YEAR(TODAY()))*'Registro de Gastos'!G4:G103) | C15: =Presupuesto!$C$2 | E15: Otros
A16: Oct | B16: =SUMPRODUCT((MONTH('Registro de Gastos'!A4:A103)=10)*(YEAR('Registro de Gastos'!A4:A103)=YEAR(TODAY()))*'Registro de Gastos'!G4:G103) | C16: =Presupuesto!$C$2
A17: Nov | B17: =SUMPRODUCT((MONTH('Registro de Gastos'!A4:A103)=11)*(YEAR('Registro de Gastos'!A4:A103)=YEAR(TODAY()))*'Registro de Gastos'!G4:G103) | C17: =Presupuesto!$C$2
A18: Dic | B18: =SUMPRODUCT((MONTH('Registro de Gastos'!A4:A103)=12)*(YEAR('Registro de Gastos'!A4:A103)=YEAR(TODAY()))*'Registro de Gastos'!G4:G103) | C18: =Presupuesto!$C$2

Sheet Presupuesto
A1: PRESUPUESTO — SOCIEDAD VARGAS MESA
A2: PRESUPUESTO TOTAL MENSUAL ($COP): | C2: 6000000 | D2: ← EDITAR AQUÍ
A3: Categoría | B3: Presupuesto ($) | C3: Gasto Real Mes ($) | D3: Desviación ($) | E3: Desviación (%) | F3: Estado
A4: Droga veterinaria | B4: 800000 | C4: =SUMPRODUCT(('Registro de Gastos'!C4:C103=A4)*(IFERROR(MONTH('Registro de Gastos'!A4:A103),0)=MONTH(TODAY()))*(IFERROR(YEAR('Registro de Gastos'!A4:A103),0)=YEAR(TODAY()))*'Registro de Gastos'!G4:G103) | D4: =C4-B4 | E4: =IF(B4=0,"-",C4/B4-1) | F4: =IF(B4=0,"-",IF(C4/B4<=0.8,"✅ Normal",IF(C4/B4<=1,"⚠ Elevado","🔴 Crítico")))
A5: Insumos | B5: 900000 | C5: =SUMPRODUCT(('Registro de Gastos'!C4:C103=A5)*(IFERROR(MONTH('Registro de Gastos'!A4:A103),0)=MONTH(TODAY()))*(IFERROR(YEAR('Registro de Gastos'!A4:A103),0)=YEAR(TODAY()))*'Registro de Gastos'!G4:G103) | D5: =C5-B5 | E5: =IF(B5=0,"-",C5/B5-1) | F5: =IF(B5=0,"-",IF(C5/B5<=0.8,"✅ Normal",IF(C5/B5<=1,"⚠ Elevado","🔴 Crítico")))
A6: Mano de obra | B6: 1200000 | C6: =SUMPRODUCT(('Registro de Gastos'!C4:C103=A6)*(IFERROR(MONTH('Registro de Gastos'!A4:A103),0)=MONTH(TODAY()))*(IFERROR(YEAR('Registro de Gastos'!A4:A103),0)=YEAR(TODAY()))*'Registro de Gastos'!G4:G103) | D6: =C6-B6 | E6: =IF(B6=0,"-",C6/B6-1) | F6: =IF(B6=0,"-",IF(C6/B6<=0.8,"✅ Normal",IF(C6/B6<=1,"⚠ Elevado","🔴 Crítico")))
A7: Equipos y mantenimiento | B7: 600000 | C7: =SUMPRODUCT(('Registro de Gastos'!C4:C103=A7)*(IFERROR(MONTH('Registro de Gastos'!A4:A103),0)=MONTH(TODAY()))*(IFERROR(YEAR('Registro de Gastos'!A4:A103),0)=YEAR(TODAY()))*'Registro de Gastos'!G4:G103) | D7: =C7-B7 | E7: =IF(B7=0,"-",C7/B7-1) | F7: =IF(B7=0,"-",IF(C7/B7<=0.8,"✅ Normal",IF(C7/B7<=1,"⚠ Elevado","🔴 Crítico")))
A8: Víveres y mercado | B8: 500000 | C8: =SUMPRODUCT(('Registro de Gastos'!C4:C103=A8)*(IFERROR(MONTH('Registro de Gastos'!A4:A103),0)=MONTH(TODAY()))*(IFERROR(YEAR('Registro de Gastos'!A4:A103),0)=YEAR(TODAY()))*'Registro de Gastos'!G4:G103) | D8: =C8-B8 | E8: =IF(B8=0,"-",C8/B8-1) | F8: =IF(B8=0,"-",IF(C8/B8<=0.8,"✅ Normal",IF(C8/B8<=1,"⚠ Elevado","🔴 Crítico")))
A9: Locativos | B9: 400000 | C9: =SUMPRODUCT(('Registro de Gastos'!C4:C103=A9)*(IFERROR(MONTH('Registro de Gastos'!A4:A103),0)=MONTH(TODAY()))*(IFERROR(YEAR('Registro de Gastos'!A4:A103),0)=YEAR(TODAY()))*'Registro de Gastos'!G4:G103) | D9: =C9-B9 | E9: =IF(B9=0,"-",C9/B9-1) | F9: =IF(B9=0,"-",IF(C9/B9<=0.8,"✅ Normal",IF(C9/B9<=1,"⚠ Elevado","🔴 Crítico")))
A10: Servicios públicos | B10: 300000 | C10: =SUMPRODUCT(('Registro de Gastos'!C4:C103=A10)*(IFERROR(MONTH('Registro de Gastos'!A4:A103),0)=MONTH(TODAY()))*(IFERROR(YEAR('Registro de Gastos'!A4:A103),0)=YEAR(TODAY()))*'Registro de Gastos'!G4:G103) | D10: =C10-B10 | E10: =IF(B10=0,"-",C10/B10-1) | F10: =IF(B10=0,"-",IF(C10/B10<=0.8,"✅ Normal",IF(C10/B10<=1,"⚠ Elevado","🔴 Crítico")))
A11: Otros | B11: 900000 | C11: =SUMPRODUCT(('Registro de Gastos'!C4:C103=A11)*(IFERROR(MONTH('Registro de Gastos'!A4:A103),0)=MONTH(TODAY()))*(IFERROR(YEAR('Registro de Gastos'!A4:A103),0)=YEAR(TODAY()))*'Registro de Gastos'!G4:G103) | D11: =C11-B11 | E11: =IF(B11=0,"-",C11/B11-1) | F11: =IF(B11=0,"-",IF(C11/B11<=0.8,"✅ Normal",IF(C11/B11<=1,"⚠ Elevado","🔴 Crítico")))
A12: TOTALES | B12: =SUM(B4:B11) | C12: =SUM(C4:C11) | D12: =C12-B12 | E12: =IF(B12=0,"-",C12/B12-1)

Sheet Plantillas de Prompt
A1: 🤖 PLANTILLAS DE PROMPT PARA CLAUDE — SOCIEDAD VARGAS MESA
A2: Copia el prompt y pégalo en Claude (claude.ai) junto con los datos de tus hojas.
A4: 📋 1. REGISTRO DIARIO DE GASTOS
A5: Soy socio de la Sociedad Vargas Mesa, fincas ganaderas y de cultivos en Aguazul y Yopal, Casanare. Necesito registrar los siguientes gastos de hoy [FECHA] en la finca [FINCA: Aguazul/Yopal/Otra]: [LISTA DE GASTOS — uno por línea o separados por coma] Ejemplo: "vacuna triple bovina x50 dosis $180.000, jornal desyerbe 3 personas $120.000 c/u, gasolina $85.000" Para cada gasto: 1. Categoría (elegir de: Sanidad animal / Alimentación animal / Insumos agrícolas / Mano de obra / Maquinaria y equipos / Transporte / Semillas y material vegetal / Administración y otros) 2. Subcategoría sugerida 3. Proveedor probable (si puedes inferirlo) 4. Cantidad, unidad y valor unitario 5. Total Responde en tabla con columnas: Fecha | Descripción | Categoría | Subcategoría | Finca | Proveedor | Cantidad | Unidad | Valor Unit. | Total | Registrado por
A21: 📊 2. ANÁLISIS MENSUAL
A22: Analiza los gastos del mes de [MES/AÑO] de la Sociedad Vargas Mesa (ganadería bovina de carne + cultivos, Aguazul y Yopal, Casanare): GASTOS REALES POR CATEGORÍA (copiar de Hoja "Resumen por Categoría"): [PEGAR DATOS AQUÍ] PRESUPUESTO MENSUAL TOTAL: $6.000.000 COP PRESUPUESTO POR CATEGORÍA (copiar de Hoja "Presupuesto"): [PEGAR DATOS AQUÍ] Análisis solicitado: 1. ¿Qué 3 categorías tuvieron mayor desviación del presupuesto? 2. ¿Hay gastos inusuales o alertas? ¿Por qué podrían haberse dado? 3. Comparación con el mes anterior (si pegas datos del mes anterior también) 4. 3 recomendaciones concretas para el próximo mes 5. Calificación general: 🟢 NORMAL / 🟡 ELEVADO / 🔴 CRÍTICO — con justificación
A38: 📅 3. COMPARATIVO ENTRE MESES
A39: Compara los gastos de la Sociedad Vargas Mesa entre dos meses: MES 1 ([MES1 — copiar de Resumen]): [DATOS MES 1] MES 2 ([MES2 — copiar de Resumen]): [DATOS MES 2] Contexto: ganadería bovina + cultivos, Llanos Orientales (Casanare), Colombia. Preguntas: 1. ¿En qué categorías aumentaron más los gastos? ¿Por qué podría ser? 2. ¿Hay patrones estacionales (temporada de lluvias, cosecha, ciclo de parición)? 3. ¿Qué categoría mejoró más en eficiencia? 4. Proyección del próximo mes basada en la tendencia 5. Semáforo por categoría: 🟢 Mejoró / 🟡 Igual / 🔴 Empeoró
A55: 🐄 4. PREPARACIÓN PARA VENTA/SUBASTA
A56: Vamos a realizar una venta de ganado bovino en [FECHA SUBASTA]. Necesito evaluar la rentabilidad: COSTOS ACUMULADOS DEL LOTE (copiar de Registro filtrado por finca/período): [DATOS DE COSTOS] DATOS DEL LOTE: - Número de cabezas: [N] - Peso promedio estimado: [KG] kg/cabeza - Precio esperado en subasta: $[PRECIO]/kg en pie - Costo de transporte a subasta: $[VALOR] Por favor: 1. Costo total por cabeza y por kg 2. Margen bruto esperado (en $ y %) 3. Precio mínimo de venta para no perder dinero (punto de equilibrio) 4. ¿Conviene vender ahora o esperar? (considera estacionalidad Casanare: precios suben dic-ene) 5. ¿Qué gastos podrían reducirse antes del próximo ciclo?
A72: 💰 5. PRESUPUESTO VS REAL
A73: Revisa la ejecución presupuestal de la Sociedad Vargas Mesa — [PERÍODO]: TABLA PRESUPUESTO VS REAL (copiar de Hoja "Presupuesto"): [PEGAR TABLA AQUÍ] Contexto: fincas en Aguazul y Yopal, Casanare. Actividad: ganadería bovina + cultivos. Necesito: 1. Categorías más desviadas (en $ y %) y posibles causas 2. ¿El presupuesto de $6.000.000/mes es realista? ¿Qué debería ajustarse? 3. Recomendación de presupuesto por categoría para el próximo ciclo 4. Proyección del gasto total anual si continúa la tendencia actual 5. ¿Hay oportunidades de ahorro sin afectar la operación?
... A90: Compara el desempeño de gastos entre fincas de la Sociedad Vargas Mesa: FINCA AGUAZUL (copiar de Resumen filtrando por Aguazul): [DATOS AGUAZUL] FINCA YOPAL (copiar de Resumen filtrando por Yopal): [DATOS YOPAL] OTRAS FINCAS (si aplica): [DATOS OTRAS] Preguntas: 1. ¿Cuál finca tiene mayor costo operativo? ¿Por cabeza o por hectárea si tienes ese dato? 2. ¿Dónde hay más oportunidades de optimización? 3. ¿Hay categorías donde una finca es más eficiente? 4. ¿Conviene centralizar compras de insumos o maquinaria entre fincas? 5. Recomendaciones para mejorar la eficiencia de la finca con mayor costo
